LICENSE
README.md
setup.cfg
setup.py
twarc_timeline_archive.py
twarc_timeline_archive.egg-info/PKG-INFO
twarc_timeline_archive.egg-info/SOURCES.txt
twarc_timeline_archive.egg-info/dependency_links.txt
twarc_timeline_archive.egg-info/entry_points.txt
twarc_timeline_archive.egg-info/requires.txt
twarc_timeline_archive.egg-info/top_level.txt