Metadata-Version: 2.1
Name: twarc-timeline-archive
Version: 0.1.3
Summary: A twarc plugin to collect the timelines of a list of users
Home-page: https://github.com/docnow/twarc-timeline-archive
Author: Ed Summers
Author-email: ehs@pobox.com
License: UNKNOWN
Platform: UNKNOWN
Requires-Python: >=3.3
License-File: LICENSE
